toolr/__init__.py
toolr/__main__.py
toolr/_context.py
toolr/_context.pyi
toolr/_exc.py
toolr/_parser.py
toolr/_registry.py
toolr/py.typed
toolr/testing.py
toolr/utils/__init__.py
toolr/utils/_console.py
toolr/utils/_docstrings.py
toolr/utils/_imports.py
toolr/utils/_logs.py
toolr/utils/_rust_utils.cpython-313-x86_64-linux-gnu.so
toolr/utils/_rust_utils.pyi
toolr/utils/_signature.py
toolr/utils/command.py
toolr-0.11.0.dist-info/METADATA
toolr-0.11.0.dist-info/WHEEL
toolr-0.11.0.dist-info/entry_points.txt
toolr-0.11.0.dist-info/RECORD
toolr-0.11.0.dist-info/licenses/LICENSE
