Metadata-Version: 2.4
Name: toolr
Version: 0.11.0
Classifier: Development Status :: 3 - Alpha
Classifier: Programming Language :: Python :: 3 :: Only
Classifier: Programming Language :: Python :: 3.11
Classifier: Programming Language :: Python :: 3.12
Classifier: Programming Language :: Python :: 3.13
Classifier: Programming Language :: Rust
Classifier: License :: OSI Approved :: Apache Software License
Requires-Dist: msgspec>=0.19.0
Requires-Dist: rich-argparse>=1.7.0
License-File: LICENSE
Summary: In-project CLI tooling support
Author-email: Pedro Algarvio <pedro@algarvio.me>
Requires-Python: >=3.11, <3.14
Project-URL: Repository, https://github.com/s0undt3ch/ToolR
Project-URL: Documentation, https://toolr.readthedocs.io
Project-URL: Issues, https://github.com/s0undt3ch/ToolR/issues
Project-URL: Changelog, https://github.com/s0undt3ch/ToolR/blob/main/CHANGELOG.md
